.gitignore
.travis.yml
MANIFEST.in
README.mdown
setup.py
mezzanine_events/__init__.py
mezzanine_events/admin.py
mezzanine_events/defaults.py
mezzanine_events/lib.py
mezzanine_events/models.py
mezzanine_events/test_urls.py
mezzanine_events/tests.py
mezzanine_events/urls.py
mezzanine_events/views.py
mezzanine_events.egg-info/PKG-INFO
mezzanine_events.egg-info/SOURCES.txt
mezzanine_events.egg-info/dependency_links.txt
mezzanine_events.egg-info/requires.txt
mezzanine_events.egg-info/top_level.txt
mezzanine_events/migrations/0001_initial.py
mezzanine_events/migrations/__init__.py
mezzanine_events/templates/pages/event.html
mezzanine_events/templates/pages/eventcontainer.html
mezzanine_events/templatetags/__init__.py
mezzanine_events/templatetags/event.py
test_project/__init__.py
test_project/local_settings.py
test_project/manage.py
test_project/settings.py
test_project/urls.py