Metadata-Version: 1.1
Name: mezzanine-events
Version: 0.1.4
Summary: Event pages for the Mezzanine CMS
Home-page: https://github.com/stbarnabas/mezzanine-events
Author: Adam Brenecki
Author-email: abrenecki@sbtc.org.au
License: UNKNOWN
Platform: UNKNOWN
Classifier: Development Status :: 4 - Beta
Classifier: Environment :: Web Environment
Classifier: Framework :: Django
Classifier: License :: OSI Approved :: MIT License
Classifier: Natural Language :: English
Classifier: Operating System :: OS Independent
Classifier: Topic :: Internet :: WWW/HTTP :: Dynamic Content
